<?xml version="1.0" encoding="utf-8"?>
<Application>
	<forms>
		<action type="add">
			<form appformnumber="COTAX" FormType="COTAX" type="0" BorderStyle="0" uid="COTAX" title="Corporate tax" visible="1" default_button="" pane="1" color="0" left="0" top="0" width="450" height="258" client_width="" client_height="" AutoManaged="0" SupportedModes="15" ObjectType="TNX_CORPTAX" mode="1">
				<datasources>
					<DataTables />
					<dbdatasources>
						<action type="add">
							<datasource tablename="@TNX_CORPTAX" />
						</action>
					</dbdatasources>
					<userdatasources>
						<action type="add" />
					</userdatasources>
				</datasources>
				<Menus />
				<items>
					<action type="add">
						<item cellHeight="16" tab_order="0" titleHeight="20" top="6" left="10" width="428" height="171" AffectsFormMode="1" description="" disp_desc="0" enabled="1" from_pane="0" to_pane="0" linkto="" right_just="0" type="127" visible="1" uid="CMtx" IsAutoGenerated="0">
							<specific layout="0" SelectionMode="2">
								<columns>
									<action type="add">
										<column backcolor="16777215" ChooseFromListIsAutoFill="0" font_size="-1" forecolor="-1" text_style="0" disp_desc="1" visible="1" AffectsFormMode="1" val_on="Y" IsAutoGenerated="0" val_off="N" title="#" width="25" editable="0" type="16" right_just="0" uid="DocEntry" sortable="0">
											<databind databound="1" table="@TNX_CORPTAX" alias="DocEntry" />
										</column>
										<column backcolor="-1" ChooseFromListIsAutoFill="0" font_size="-1" forecolor="-1" text_style="0" disp_desc="1" visible="1" AffectsFormMode="1" val_on="Y" IsAutoGenerated="0" val_off="N" title="Code" width="80" editable="1" type="16" right_just="0" uid="Code" sortable="0">
											<databind databound="1" table="@TNX_CORPTAX" alias="Code" />
										</column>
										<column disp_desc="1" visible="1" AffectsFormMode="1" val_on="Y" IsAutoGenerated="0" val_off="N" title="Start Period" width="80" editable="1" type="113" right_just="0" uid="CMR" sortable="0">
											<databind databound="1" table="@TNX_CORPTAX" alias="U_CMR" />
											<ValidValues>
												<action type="add">
													<ValidValue value="1" description="January" />
													<ValidValue value="2" description="February" />
													<ValidValue value="3" description="March" />
													<ValidValue value="4" description="April" />
													<ValidValue value="5" description="May" />
													<ValidValue value="6" description="June" />
													<ValidValue value="7" description="July" />
													<ValidValue value="8" description="August" />
													<ValidValue value="9" description="September" />
													<ValidValue value="10" description="October" />
													<ValidValue value="11" description="November" />
													<ValidValue value="12" description="December" />
												</action>
											</ValidValues>
										</column>
										<column disp_desc="1" visible="1" AffectsFormMode="1" val_on="Y" IsAutoGenerated="0" val_off="N" title="End Period" width="80" editable="1" type="113" right_just="0" uid="SO" sortable="0">
											<databind databound="1" table="@TNX_CORPTAX" alias="U_SO" />
											<ValidValues>
												<action type="add">
													<ValidValue value="1" description="January" />
													<ValidValue value="2" description="February" />
													<ValidValue value="3" description="March" />
													<ValidValue value="4" description="April" />
													<ValidValue value="5" description="May" />
													<ValidValue value="6" description="June" />
													<ValidValue value="7" description="July" />
													<ValidValue value="8" description="August" />
													<ValidValue value="9" description="September" />
													<ValidValue value="10" description="October" />
													<ValidValue value="11" description="November" />
													<ValidValue value="12" description="December" />
												</action>
											</ValidValues>
										</column>
										<column backcolor="-1" ChooseFromListIsAutoFill="0" font_size="-1" forecolor="-1" text_style="0" disp_desc="1" visible="1" AffectsFormMode="1" val_on="Y" IsAutoGenerated="0" val_off="N" title="Alert Before" width="50" editable="1" type="16" right_just="0" uid="GRPO" sortable="0">
											<databind databound="1" table="@TNX_CORPTAX" alias="U_GRPO" />
										</column>
										<column backcolor="-1" ChooseFromListIsAutoFill="0" font_size="-1" forecolor="-1" text_style="0" disp_desc="1" visible="1" AffectsFormMode="1" val_on="Y" IsAutoGenerated="0" val_off="N" title="Submission Date" width="50" editable="1" type="16" right_just="0" uid="DCNF" sortable="0">
											<databind databound="1" table="@TNX_CORPTAX" alias="U_DCNF" />
										</column>
										<column disp_desc="1" visible="1" AffectsFormMode="1" val_on="Y" IsAutoGenerated="0" val_off="N" title="Status" width="50" editable="1" type="113" right_just="0" uid="CMN" sortable="0">
											<databind databound="1" table="@TNX_CORPTAX" alias="U_CMN" />
											<ValidValues>
												<action type="add">
													<ValidValue value="O" description="Open" />
													<ValidValue value="C" description="Closed" />
												</action>
											</ValidValues>
										</column>
									</action>
								</columns>
							</specific>
						</item>
						<item top="187" left="10" width="65" height="20" AffectsFormMode="1" description="" disp_desc="0" enabled="1" from_pane="0" to_pane="0" linkto="" right_just="0" type="4" visible="1" uid="1" IsAutoGenerated="0">
							<specific caption="Add" />
						</item>
						<item top="187" left="83" width="65" height="20" AffectsFormMode="1" description="" disp_desc="0" enabled="1" from_pane="0" to_pane="0" linkto="" right_just="0" type="4" visible="1" uid="2" IsAutoGenerated="0">
							<specific caption="Cancel" />
						</item>
					</action>
				</items>
				<ChooseFromListCollection>
					<action type="add">
						<ChooseFromList UniqueID="-1" ObjectType="-1" MultiSelection="0" IsSystem="1" />
					</action>
				</ChooseFromListCollection>
				<DataBrowser BrowseBy="DocNum" />
				<Settings MatrixUID="" Enabled="0" EnableRowFormat="0" />
			</form>
		</action>
	</forms>
</Application>